dpm2/__init__.py
dpm2/dpm.sqlite
dpm2/models.py
dpm2/py.typed
dpm2/utils.py
dpm2-2025.8.14.dist-info/WHEEL
dpm2-2025.8.14.dist-info/METADATA
dpm2-2025.8.14.dist-info/RECORD
