Metadata-Version: 2.3
Name: dpm2
Version: 2025.8.14
Summary: SQLite db and generated Python models for EBA DPM 2.0 databases with full type safety
Author: Jim Lundin
Author-email: Jim Lundin <jimeriklundin@gmail.com>
Requires-Dist: sqlalchemy>=2.0.37
Requires-Python: >=3.13
